keyboardhumanizer/__init__.py
keyboardhumanizer/humanizer.py
keyboardhumanizer/linux_engine.py
keyboardhumanizer/mac_engine.py
keyboardhumanizer/typing_engine.py
keyboardhumanizer/typing_profiles.py
keyboardhumanizer/windows_engine.py
keyboardhumanizer-0.2.0.dist-info/licenses/LICENSE
keyboardhumanizer-0.2.0.dist-info/METADATA
keyboardhumanizer-0.2.0.dist-info/WHEEL
keyboardhumanizer-0.2.0.dist-info/top_level.txt
keyboardhumanizer-0.2.0.dist-info/RECORD
