Metadata-Version: 2.4
Name: keyboardhumanizer
Version: 0.2.0
Summary: Human-like keyboard automation
Author: Your Name
Requires-Python: >=3.7
License-File: LICENSE
Dynamic: author
Dynamic: license-file
Dynamic: requires-python
Dynamic: summary
